parsely_slackbot/__init__.py
parsely_slackbot/alerts.py
parsely_slackbot/app.py
parsely_slackbot/slackbot.py
parsely_slackbot-1.1.0.dist-info/DESCRIPTION.rst
parsely_slackbot-1.1.0.dist-info/METADATA
parsely_slackbot-1.1.0.dist-info/RECORD
parsely_slackbot-1.1.0.dist-info/WHEEL
parsely_slackbot-1.1.0.dist-info/entry_points.txt
parsely_slackbot-1.1.0.dist-info/metadata.json
parsely_slackbot-1.1.0.dist-info/top_level.txt
