Metadata-Version: 2.0
Name: parsely-slackbot
Version: 1.1.0
Summary: Parsely slackbot is a slack custom integration that uses the Parsely API to allow realtime Slackalytics in your Slack instance.
Home-page: https://github.com/Parsely/slackbot
Author: Parsely, Inc.
Author-email: support@parsely.com
License: Apache License 2.0
Platform: UNKNOWN
Requires-Dist: Flask-Slack (>=0.1.5)
Requires-Dist: python-parsely
Requires-Dist: pyyaml
Requires-Dist: requests
Requires-Dist: tornado
Requires-Dist: tzlocal (>=1.2)
Provides-Extra: all
Requires-Dist: Flask-Slack (>=0.1.5); extra == 'all'
Requires-Dist: mock; extra == 'all'
Requires-Dist: pytest; extra == 'all'
Requires-Dist: python-parsely; extra == 'all'
Requires-Dist: pyyaml; extra == 'all'
Requires-Dist: requests; extra == 'all'
Requires-Dist: tornado; extra == 'all'
Requires-Dist: tzlocal (>=1.2); extra == 'all'
Provides-Extra: test
Requires-Dist: mock; extra == 'test'
Requires-Dist: pytest; extra == 'test'
